subfinder/__init__.py
subfinder/run.py
subfinder/run_gevent.py
subfinder/run_thread.py
subfinder/subfinder.py
subfinder/subfinder_gevent.py
subfinder/subfinder_thread.py
subfinder/subsearcher/__init__.py
subfinder/subsearcher/exceptions.py
subfinder/subsearcher/shooter.py
subfinder/subsearcher/subhd.py
subfinder/subsearcher/subsearcher.py
subfinder/subsearcher/zimuku.py
subfinder/tools/__init__.py
subfinder/tools/compressed_file.py
subfinder/tools/unrar.exe
subfinder/utils.py
subfinder-2.2.1.dist-info/entry_points.txt
subfinder-2.2.1.dist-info/LICENSE
subfinder-2.2.1.dist-info/WHEEL
subfinder-2.2.1.dist-info/METADATA
subfinder-2.2.1.dist-info/RECORD
