Metadata-Version: 2.1
Name: subfinder
Version: 2.2.1
Summary: subfinder -- a general finder for subtitles
Home-page: https://github.com/ausaki/subfinder/
License: MIT
Keywords: subtitle,subfinder,shooter,zimuku
Author: ausaki
Author-email: ljm51689@gmail.com
Requires-Python: >=3.5.0
Classifier: License :: OSI Approved :: MIT License
Classifier: Programming Language :: Python :: 3
Classifier: Programming Language :: Python :: 3.5
Classifier: Programming Language :: Python :: 3.6
Classifier: Programming Language :: Python :: 3.7
Classifier: Programming Language :: Python :: 3.8
Classifier: Programming Language :: Python :: 3.9
Requires-Dist: beautifulsoup4 (>=4.9.3,<5.0.0)
Requires-Dist: gevent (>=21.1.2,<22.0.0)
Requires-Dist: lxml
Requires-Dist: rarfile
Requires-Dist: requests
Requires-Dist: six
Project-URL: Repository, https://github.com/ausaki/subfinder/
